setup.py
gndb_distributions/BinomialDistribution.py
gndb_distributions/GaussianDistribution.py
gndb_distributions/GeneralDistribution.py
gndb_distributions/__init__.py
gndb_distributions/test.py
gndb_distributions.egg-info/PKG-INFO
gndb_distributions.egg-info/SOURCES.txt
gndb_distributions.egg-info/dependency_links.txt
gndb_distributions.egg-info/not-zip-safe
gndb_distributions.egg-info/top_level.txt