Metadata-Version: 1.0
Name: gndb-distributions
Version: 0.1
Summary: Gaussian and Binomial gndb_distributions
Home-page: UNKNOWN
Author: Ufuoma Ubor
Author-email: foskynew@gmail.com
License: UNKNOWN
Platform: UNKNOWN
